README.rst
setup.cfg
setup.py
project_archer/__init__.py
project_archer/mainapp.py
project_archer/project.py
project_archer.egg-info/PKG-INFO
project_archer.egg-info/SOURCES.txt
project_archer.egg-info/dependency_links.txt
project_archer.egg-info/entry_points.txt
project_archer.egg-info/requires.txt
project_archer.egg-info/top_level.txt
project_archer/environment/__init__.py
project_archer/environment/environment.py
project_archer/environment/read_shell_parameters.py
project_archer/operations/__init__.py
project_archer/operations/clear_zone.py
project_archer/operations/create_project.py
project_archer/operations/edit_project.py
project_archer/operations/empty_run.py
project_archer/operations/list_projects.py
project_archer/operations/select_project.py
project_archer/operations/select_zone.py
project_archer/storage/__init__.py
project_archer/storage/project_data.py