Metadata-Version: 1.0
Name: project-archer
Version: 0.3.2
Summary: Switch projects with ease.
Home-page: UNKNOWN
Author: Bogdan Mustiata
Author-email: bogdan.mustiata@gmail.com
License: BSD
Platform: UNKNOWN
